linkedin_scraper/__init__.py
linkedin_scraper/callbacks.py
linkedin_scraper/core/__init__.py
linkedin_scraper/core/auth.py
linkedin_scraper/core/browser.py
linkedin_scraper/core/exceptions.py
linkedin_scraper/core/utils.py
linkedin_scraper/models/__init__.py
linkedin_scraper/models/company.py
linkedin_scraper/models/job.py
linkedin_scraper/models/person.py
linkedin_scraper/scrapers/__init__.py
linkedin_scraper/scrapers/base.py
linkedin_scraper/scrapers/company.py
linkedin_scraper/scrapers/job.py
linkedin_scraper/scrapers/job_search.py
linkedin_scraper/scrapers/person.py
linkedin_scraper-3.0.1.dist-info/licenses/LICENSE
linkedin_scraper-3.0.1.dist-info/METADATA
linkedin_scraper-3.0.1.dist-info/WHEEL
linkedin_scraper-3.0.1.dist-info/top_level.txt
linkedin_scraper-3.0.1.dist-info/RECORD
