Metadata-Version: 2.4
Name: linkedin_scraper
Version: 3.0.1
Summary: Async LinkedIn scraper for profiles, companies, and jobs
Home-page: https://github.com/joeyism/linkedin_scraper
Download-URL: https://github.com/joeyism/linkedin_scraper/archive/refs/tags/3.0.1.tar.gz
Author: Joey Sham
Author-email: Joey Sham <sham.joey@gmail.com>
License: Apache 2.0
Project-URL: Homepage, https://github.com/joeyism/linkedin_scraper
Project-URL: Documentation, https://github.com/joeyism/linkedin_scraper#readme
Project-URL: Repository, https://github.com/joeyism/linkedin_scraper
Project-URL: Issues, https://github.com/joeyism/linkedin_scraper/issues
Keywords: linkedin,scraping,scraper,async,playwright,profiles
Classifier: Development Status :: 3 - Alpha
Classifier: Intended Audience :: Developers
Classifier: Topic :: Software Development :: Libraries :: Python Modules
Classifier: Topic :: Internet :: WWW/HTTP :: Dynamic Content
Classifier: License :: OSI Approved :: Apache Software License
Classifier: Programming Language :: Python :: 3
Classifier: Programming Language :: Python :: 3.8
Classifier: Programming Language :: Python :: 3.9
Classifier: Programming Language :: Python :: 3.10
Classifier: Programming Language :: Python :: 3.11
Classifier: Programming Language :: Python :: 3.12
Classifier: Operating System :: OS Independent
Requires-Python: >=3.8
License-File: LICENSE
Requires-Dist: playwright>=1.40.0
Requires-Dist: requests>=2.31.0
Requires-Dist: lxml>=5.0.0
Requires-Dist: pydantic>=2.0.0
Requires-Dist: python-dotenv>=1.0.0
Requires-Dist: aiofiles>=23.0.0
Provides-Extra: dev
Requires-Dist: pytest>=7.0.0; extra == "dev"
Requires-Dist: pytest-asyncio>=0.21.0; extra == "dev"
Requires-Dist: pytest-cov>=4.0.0; extra == "dev"
Requires-Dist: build>=1.0.0; extra == "dev"
Requires-Dist: twine>=4.0.0; extra == "dev"
Requires-Dist: wheel>=0.40.0; extra == "dev"
Dynamic: author
Dynamic: download-url
Dynamic: home-page
Dynamic: license-file
Dynamic: requires-python
